{"comment": "//leave comments here if needed", "contain_publication_list": "F", "email": "ab269@le.ac.uk", "filename": "5344cd95-5537-4746-b953-1b4dc83a8bd4", "info": "T means true, F means False. If no publications, just leave the publication structure unchanged.", "is_personal_homepage": "T", "name": "Arnoud Boom", "name_index": [{"index_in_file": [[202, 213], [217, 228], [2265, 2276]], "name_format": "Begin_First_Full End_Last_Full", "text": "Arnoud Boom"}, {"in_email": "Before_At", "index_in_file": [[333, 335], [544, 546], [558, 560], [658, 660], [750, 752], [764, 766], [1237, 1239], [1344, 1346], [1639, 1641], [1923, 1925], [2277, 2279], [2629, 2631]], "name_format": "Begin_First_Initial_Last_Initial", "text": "ab"}], "publications": [{"text": "COPY_SINGLE_PUBLICATION_HERE"}, {"text": "COPY_SINGLE_PUBLICATION_HERE"}], "url": "http://www2.le.ac.uk/departments/geography/people/ab269", "affiliation_info": [{"author_title": {"line_num": 9, "text": "Dr"}}, {"affiliation": {"line_num": 8, "text": "Department of Geography"}}, {"position": {"line_num": 11, "text": "Senior Lecturer"}}]}