[{"begin": 0, "end": 52, "text": "Huang, W.M., Yang, B., An, L., Li, C. and Chan, Y.S.", "tokenized_text": "Huang , W . M . , Yang , B . , An , L . , Li , C . and Chan , Y . S .", "type": "authors", "id": 0}, {"begin": 54, "end": 142, "text": "Water-driven programmable polyurethane shape memory polymer: demonstration and mechanism", "tokenized_text": "Water - driven programmable polyurethane shape memory polymer : demonstration and mechanism", "type": "title", "id": 1}, {"begin": 144, "end": 167, "text": "Applied Physics Letters", "tokenized_text": "Applied Physics Letters", "type": "venue", "id": 2}, {"begin": 177, "end": 181, "text": "2005", "tokenized_text": "2005", "type": "year", "id": 3}]