[{"begin": 0, "end": 63, "text": "Palm, H., Wismans, L.J.J., Mede, P.H.J. van der & Kievit, E. de", "tokenized_text": "Palm , H . , Wismans , L . J . J . , Mede , P . H . J . van der & Kievit , E . de", "type": "authors", "id": 0}, {"begin": 65, "end": 69, "text": "2015", "tokenized_text": "2015", "type": "year", "id": 1}, {"begin": 72, "end": 157, "text": "Combining new data gathering technology to investigate pedestrian movements in cities", "tokenized_text": "Combining new data gathering technology to investigate pedestrian movements in cities", "type": "title", "id": 2}, {"begin": 162, "end": 165, "text": "ITS", "tokenized_text": "ITS", "type": "venue", "id": 3}, {"begin": 188, "end": 211, "text": "22nd ITS World Congress", "tokenized_text": "22nd ITS World Congress", "type": "venue", "id": 4}, {"begin": 225, "end": 229, "text": "2015", "tokenized_text": "2015", "type": "year", "id": 5}]