[{"begin": 0, "end": 117, "text": "“Intrinsically proton conducting polymers and copolymers containing benzimidazole moieties: Glass transition effect", "tokenized_text": "“Intrinsically proton conducting polymers and copolymers containing benzimidazole moieties : Glass transition effects ,", "type": "title", "id": 0}, {"begin": 117, "end": 156, "text": "s,” Woudenberg RC, Yavuzcetin O, Tuom", "tokenized_text": "” Woudenberg RC , Yavuzcetin O , Tuominen", "type": "authors", "id": 1}, {"begin": 161, "end": 172, "text": "MT, Coughli", "tokenized_text": "Coughlin EB", "type": "venue", "id": 2}, {"begin": 174, "end": 192, "text": "EB, Solid State Io", "tokenized_text": "Solid State Ionics", "type": "venue", "id": 3}, {"begin": 209, "end": 213, "text": "41 (", "tokenized_text": "2007", "type": "year", "id": 4}]