[{"begin": 0, "end": 74, "text": "Gravem, D., Lakes, K. D., Teran, L., Rich, J., Cooper, D., & Olshansky, E.", "tokenized_text": "Gravem , D . , Lakes , K . D . , Teran , L . , Rich , J . , Cooper , D . , & Olshansky , E .", "type": "authors", "id": 0}, {"begin": 76, "end": 80, "text": "2009", "tokenized_text": "2009", "type": "year", "id": 1}, {"begin": 83, "end": 161, "text": "Maternal perceptions of a neonatal intensive care unit infant exercise program", "tokenized_text": "Maternal perceptions of a neonatal intensive care unit infant exercise program", "type": "title", "id": 2}, {"begin": 163, "end": 173, "text": "Journal of", "tokenized_text": "Journal of", "type": "venue", "id": 3}, {"begin": 185, "end": 218, "text": "Gynecologic, and Neonatal Nursing", "tokenized_text": "Gynecologic , and Neonatal Nursing", "type": "venue", "id": 4}]