[{"begin": 0, "end": 22, "text": "Caldas, L., Duarte, J.", "tokenized_text": "Caldas , L . , Duarte , J .", "type": "authors", "id": 0}, {"begin": 24, "end": 28, "text": "2005", "tokenized_text": "2005", "type": "year", "id": 1}, {"begin": 30, "end": 119, "text": "‚ÄúFabricating Innovative Ceramic Covers: Re-Thinking Roof Tiles in a Contemporary Contex", "tokenized_text": "‚ÄúFabricating Innovative Ceramic Covers : Re - Thinking Roof Tiles in a Contemporary Context‚Äù", "type": "title", "id": 2}, {"begin": 121, "end": 125, "text": "Äù, ", "tokenized_text": "Proc", "type": "venue", "id": 3}, {"begin": 127, "end": 136, "text": "oc. ECAAD", "tokenized_text": "ECAADE‚Äô05", "type": "venue", "id": 4}]