{"comment": "//leave comments here if needed", "contain_publication_list": "F", "email": "", "filename": "eed25a7c-184c-4586-b365-327f4645fd9f", "info": "T means true, F means False. If no publications, just leave the publication structure unchanged.", "is_personal_homepage": "T", "name": "Carroll E. Cross", "name_index": [{"index_in_file": [[158, 174], [324, 340]], "name_format": "Begin_First_Full Inside_Middle_Initial End_Last_Full", "text": "Carroll E. Cross"}, {"index_in_file": [[940, 945]], "name_format": "Begin_Last_Full", "text": "Cross"}], "publications": [{"text": "COPY_SINGLE_PUBLICATION_HERE"}, {"text": "COPY_SINGLE_PUBLICATION_HERE"}], "url": "http://www.ucdmc.ucdavis.edu/publish/facultybio/internalmedicine/260", "affiliation_info": [{"author_title": {"line_num": 17, "text": "Professor"}}, {"affiliation": {"line_num": 5, "text": "Department of Internal Medicine"}}, {"position": {"line_num": 31, "text": "co-director"}}]}