[{"begin": 0, "end": 23, "text": "Özçelik, Öner. Accep", "tokenized_text": "Özçelik , Öner . Accepted", "type": "authors", "id": 0}, {"begin": 25, "end": 116, "text": "d. Acquisition of L2 Turkish prosody: effects of purely phonological and phonosyntactic iss", "tokenized_text": "Acquisition of L2 Turkish prosody : effects of purely phonological and phonosyntactic issues", "type": "title", "id": 1}, {"begin": 126, "end": 133, "text": "şe Gü", "tokenized_text": "Gürel &", "type": "venue", "id": 2}, {"begin": 158, "end": 196, "text": "s.), Second Language Acquisition of Tu", "tokenized_text": "Second Language Acquisition of Turkish", "type": "venue", "id": 3}]