[{"begin": 136, "end": 208, "text": "Based Education On A Perinatal Capacity-Building Initiative In Macedonia", "tokenized_text": "Based Education On A Perinatal Capacity - Building Initiative In Macedonia", "type": "title", "id": 0}, {"begin": 210, "end": 234, "text": "Medical Education Online", "tokenized_text": "Medical Education Online", "type": "venue", "id": 1}, {"begin": 0, "end": 104, "text": "Jeffery, H., Kocova, M., Tozija, F., Gjorgiev, D., Pop-Lazarova, M., Foster, K., Polverino, J., Hill, D.", "tokenized_text": "Jeffery , H . , Kocova , M . , Tozija , F . , Gjorgiev , D . , Pop - Lazarova , M . , Foster , K . , Polverino , J . , Hill , D .", "type": "authors", "id": 2}, {"begin": 106, "end": 110, "text": "2004", "tokenized_text": "2004", "type": "year", "id": 3}, {"begin": 113, "end": 136, "text": "The Impact Of Evidence-", "tokenized_text": "The Impact Of Evidence -", "type": "title", "id": 4}]