[{"begin": 0, "end": 27, "text": "Mitchell J. Morris, John R.", "tokenized_text": "Mitchell J . Morris , John R .", "type": "authors", "id": 0}, {"begin": 28, "end": 34, "text": "Kender", "tokenized_text": "Kender", "type": "title", "id": 1}, {"begin": 38, "end": 126, "text": "Sort-Merge feature selection and fusion methods for classification of unstructured video", "tokenized_text": "Sort - Merge feature selection and fusion methods for classification of unstructured video", "type": "title", "id": 2}, {"begin": 130, "end": 134, "text": "ICME", "tokenized_text": "ICME", "type": "venue", "id": 3}, {"begin": 135, "end": 139, "text": "2009", "tokenized_text": "2009", "type": "year", "id": 4}]