[{"begin": 114, "end": 154, "text": ". C., Yeates, S. J. and Brinsmead, R. B.", "tokenized_text": ". C . , Yeates , S . J . and Brinsmead , R . B .", "type": "authors", "id": 0}, {"begin": 156, "end": 160, "text": "2002", "tokenized_text": "2002", "type": "year", "id": 1}, {"begin": 162, "end": 233, "text": "Simulation of growth and development of diverse legume species in APSIM", "tokenized_text": "Simulation of growth and development of diverse legume species in APSIM", "type": "title", "id": 2}, {"begin": 235, "end": 278, "text": "Australian Journal of Agricultural Research", "tokenized_text": "Australian Journal of Agricultural Research", "type": "venue", "id": 3}, {"begin": 0, "end": 114, "text": "Robertson, M. J., Carberry, P. S., Huth, N. I., Turpin, J. E., Probert, M. E., Poulton, P. L., Bell, M., Wright, G", "tokenized_text": "Robertson , M . J . , Carberry , P . S . , Huth , N . I . , Turpin , J . E . , Probert , M . E . , Poulton , P . L . , Bell , M . , Wright , G", "type": "authors", "id": 4}]