[{"begin": 0, "end": 33, "text": "Bell, MJ, Wright, GC and Harch, G", "tokenized_text": "Bell , MJ , Wright , GC and Harch , G", "type": "authors", "id": 0}, {"begin": 35, "end": 39, "text": "1993", "tokenized_text": "1993", "type": "year", "id": 1}, {"begin": 41, "end": 141, "text": "Environmental and Agronomic Effects On the Growth of 4 Peanut Cultivars in a Subtropical Environment", "tokenized_text": "Environmental and Agronomic Effects On the Growth of 4 Peanut Cultivars in a Subtropical Environment", "type": "title", "id": 2}, {"begin": 146, "end": 169, "text": "Dry-Matter Partitioning", "tokenized_text": "Dry - Matter Partitioning", "type": "title", "id": 3}, {"begin": 171, "end": 195, "text": "Experimental Agriculture", "tokenized_text": "Experimental Agriculture", "type": "venue", "id": 4}]