[{"begin": 133, "end": 137, "text": "(201", "tokenized_text": "2013", "type": "year", "id": 0}, {"begin": 140, "end": 190, "text": "\"Ba Double Gamma Decay Measurement with GAMMASPHER", "tokenized_text": "Ba Double Gamma Decay Measurement with GAMMASPHERE", "type": "title", "id": 1}, {"begin": 0, "end": 130, "text": "Merchán, E., Moran, K., Lister, C.J., Chowdhury, P., McCutchan, E., Greene, J., Zhu, S., Lauritsen, T., Carpenter, M., Shearman, ", "tokenized_text": "Merchán , E . , Moran , K . , Lister , C . J . , Chowdhury , P . , McCutchan , E . , Greene , J . , Zhu , S . , Lauritsen , T . , Carpenter , M . , Shearman , R", "type": "authors", "id": 2}]