[{"begin": 157, "end": 167, "text": "t of IceCu", "tokenized_text": "of IceCube", "type": "title", "id": 0}, {"begin": 168, "end": 220, "text": "e.”Nuclear Instruments and Methods in Physics Rese", "tokenized_text": "”Nuclear Instruments and Methods in Physics Research", "type": "venue", "id": 1}, {"begin": 0, "end": 119, "text": "Abbasi, R., Y. Abdou, M. Ackermann, J. Adams, J. Aguilar, M. Ahlers, D. Altmann, K. Andeen, J. Auffenberg, X. Bai et al", "tokenized_text": "Abbasi , R . , Y . Abdou , M . Ackermann , J . Adams , J . Aguilar , M . Ahlers , D . Altmann , K . Andeen , J . Auffenberg , X . Bai et al", "type": "authors", "id": 2}, {"begin": 121, "end": 125, "text": "2013", "tokenized_text": "2013", "type": "year", "id": 3}, {"begin": 126, "end": 156, "text": "“IceTop: The surface compone", "tokenized_text": "“IceTop : The surface component", "type": "title", "id": 4}]