{"comment": "//leave comments here if needed", "contain_publication_list": "F", "email": "W.Gittens@sussex.ac.uk", "filename": "bde65a48-8ba8-4fde-9ad3-aadab495fac2", "info": "T means true, F means False. If no publications, just leave the publication structure unchanged.", "is_personal_homepage": "T", "name": "William Gittens", "name_index": [{"index_in_file": [[181, 196], [328, 343], [382, 397]], "name_format": "Begin_First_Full End_Last_Full", "text": "William Gittens"}, {"in_email": "BEFORE_AT", "index_in_file": [[532, 541]], "name_format": "Begin_First_Initial End_Last_Full", "text": "W.Gittens"}], "publications": [{"text": "COPY_SINGLE_PUBLICATION_HERE"}, {"text": "COPY_SINGLE_PUBLICATION_HERE"}], "url": "http://www.sussex.ac.uk/gdsc/people/person/321166", "affiliation_info": [{"affiliation": {"line_num": 12, "text": "School of Life Sciences"}}, {"position": {"line_num": 28, "text": "Research Fellow"}}]}