[{"begin": 246, "end": 310, "text": "for application in a phase I trial in non-small cell lung cancer", "tokenized_text": "for application in a phase I trial in non - small cell lung cancer", "type": "title", "id": 0}, {"begin": 312, "end": 345, "text": "Journal of translational medicine", "tokenized_text": "Journal of translational medicine", "type": "venue", "id": 1}, {"begin": 347, "end": 351, "text": "2008", "tokenized_text": "2008", "type": "year", "id": 2}, {"begin": 0, "end": 166, "text": "Baratelli Felicita, Takedatsu Hiroko, Hazra Saswati, Peebles Katherine, Luo Jie, Kurimoto Pam S, Zeng Gang, Batra Raj K, Sharma Sherven, Dubinett Steven M, Lee Jay M,", "tokenized_text": "Baratelli Felicita , Takedatsu Hiroko , Hazra Saswati , Peebles Katherine , Luo Jie , Kurimoto Pam S , Zeng Gang , Batra Raj K , Sharma Sherven , Dubinett Steven M , Lee Jay M ,", "type": "authors", "id": 3}, {"begin": 167, "end": 245, "text": "Pre-clinical characterization of GMP grade CCL21-gene modified dendritic cells", "tokenized_text": "Pre - clinical characterization of GMP grade CCL21 - gene modified dendritic cells", "type": "title", "id": 4}]