[{"begin": 0, "end": 164, "text": "Dalwadi Harnisha, Krysan Kostyantyn, Heuze-Vourc'h Nathalie, Dohadwala Mariam, Elashoff David, Sharma Sherven, Cacalano Nicholas, Lichtenstein Alan, Dubinett Steven", "tokenized_text": "Dalwadi Harnisha , Krysan Kostyantyn , Heuze - Vourc ' h Nathalie , Dohadwala Mariam , Elashoff David , Sharma Sherven , Cacalano Nicholas , Lichtenstein Alan , Dubinett Steven", "type": "authors", "id": 0}, {"begin": 166, "end": 277, "text": "Cyclooxygenase-2-dependent activation of signal transducer and activator of transcription 3 by interleukin-6 in", "tokenized_text": "Cyclooxygenase - 2 - dependent activation of signal transducer and activator of transcription 3 by interleukin - 6 in", "type": "title", "id": 1}, {"begin": 278, "end": 304, "text": "non-small cell lung cancer", "tokenized_text": "non - small cell lung cancer", "type": "title", "id": 2}, {"begin": 306, "end": 400, "text": "Clinical cancer research : an official journal of the American Association for Cancer Research", "tokenized_text": "Clinical cancer research : an official journal of the American Association for Cancer Research", "type": "venue", "id": 3}, {"begin": 402, "end": 406, "text": "2005", "tokenized_text": "2005", "type": "year", "id": 4}]