[{"begin": 0, "end": 40, "text": "Zwischen Naturwissenschaft und Esoterium", "tokenized_text": "Zwischen Naturwissenschaft und Esoterium", "type": "title", "id": 0}, {"begin": 44, "end": 101, "text": "Von Fechner zu Freud und Bergson\nkeyword : Fechner, Freud", "tokenized_text": "Von Fechner zu Freud und Bergson keyword : Fechner , Freud", "type": "title", "id": 1}, {"begin": 103, "end": 110, "text": "Bergson", "tokenized_text": "Bergson", "type": "venue", "id": 2}, {"begin": 112, "end": 124, "text": "Psychophysik", "tokenized_text": "Psychophysik", "type": "venue", "id": 3}, {"begin": 149, "end": 160, "text": "des Geistes", "tokenized_text": "des Geistes", "type": "venue", "id": 4}, {"begin": 161, "end": 165, "text": "2012", "tokenized_text": "2012", "type": "year", "id": 5}]