[{"begin": 0, "end": 7, "text": "Wang J.", "tokenized_text": "Wang J .", "type": "authors", "id": 0}, {"begin": 8, "end": 87, "text": "Checking before changing: cell cycle checkpoints inhibit muscle differentiation", "tokenized_text": "Checking before changing : cell cycle checkpoints inhibit muscle differentiation", "type": "title", "id": 1}, {"begin": 89, "end": 99, "text": "Cell Cycle", "tokenized_text": "Cell Cycle", "type": "venue", "id": 2}, {"begin": 101, "end": 105, "text": "2011", "tokenized_text": "2011", "type": "year", "id": 3}]