[{"begin": 0, "end": 148, "text": "Flow and transport effects of compaction bands in sandstone at scales relevant to aquifer and reservoir management WATER RESOURCES RESEARCH Sternlof", "tokenized_text": "Flow and transport effects of compaction bands in sandstone at scales relevant to aquifer and reservoir management WATER RESOURCES RESEARCH Sternlof", "type": "title", "id": 0}, {"begin": 150, "end": 205, "text": "K. R., Karimi-Fard, M., Pollard, D. D., Durlofsky, L. J", "tokenized_text": "K . R . , Karimi - Fard , M . , Pollard , D . D . , Durlofsky , L . J", "type": "authors", "id": 1}, {"begin": 207, "end": 211, "text": "2006", "tokenized_text": "2006", "type": "year", "id": 2}]