[{"begin": 254, "end": 257, "text": "MCR", "tokenized_text": "MCR", "type": "venue", "id": 0}, {"begin": 259, "end": 263, "text": "2006", "tokenized_text": "2006", "type": "year", "id": 1}, {"begin": 0, "end": 160, "text": "Tso Cho-Lea, Shintaku Peter, Chen James, Liu Qinghai, Liu Jason, Chen Zugen, Yoshimoto Koji, Mischel Paul S, Cloughesy Timothy F, Liau Linda M, Nelson Stanley F", "tokenized_text": "Tso Cho - Lea , Shintaku Peter , Chen James , Liu Qinghai , Liu Jason , Chen Zugen , Yoshimoto Koji , Mischel Paul S , Cloughesy Timothy F , Liau Linda M , Nelson Stanley F", "type": "authors", "id": 2}, {"begin": 163, "end": 253, "text": "Primary glioblastomas express mesenchymal stem-like properties Molecular cancer research :", "tokenized_text": "Primary glioblastomas express mesenchymal stem - like properties Molecular cancer research :", "type": "title", "id": 3}]