[{"begin": 4, "end": 36, "text": "M. Ohtaki, K. Araki, K. Yamamoto", "tokenized_text": "M . Ohtaki , K . Araki , K . Yamamoto", "type": "authors", "id": 0}, {"begin": 38, "end": 98, "text": "High Thermoelectric Performance of Dually Doped ZnO Ceramics", "tokenized_text": "High Thermoelectric Performance of Dually Doped ZnO Ceramics", "type": "title", "id": 1}, {"begin": 100, "end": 131, "text": "Journal of Electronic Materials", "tokenized_text": "Journal of Electronic Materials", "type": "venue", "id": 2}]