[{"begin": 0, "end": 10, "text": "Gibson, R.", "tokenized_text": "Gibson , R .", "type": "authors", "id": 0}, {"begin": 12, "end": 16, "text": "2008", "tokenized_text": "2008", "type": "year", "id": 1}, {"begin": 19, "end": 61, "text": "Vision and Disintegration (Public Lecture)", "tokenized_text": "Vision and Disintegration ( Public Lecture )", "type": "title", "id": 2}, {"begin": 63, "end": 142, "text": "Visual Cultures and Colonialism: Indigeneity in Local and Transnational Imagery", "tokenized_text": "Visual Cultures and Colonialism : Indigeneity in Local and Transnational Imagery", "type": "venue", "id": 3}]