[{"begin": 0, "end": 67, "text": "Chen, H.; Navea, J. G.; Young, M. A.; Grassian, V.H. “Heterogeneo", "tokenized_text": "Chen , H . ; Navea , J . G . ; Young , M . A . ; Grassian , V . H . “Heterogeneous", "type": "authors", "id": 0}, {"begin": 68, "end": 150, "text": "s Photochemistry of Trace Atmospheric Gases with Components of Mineral Dust Aeroso", "tokenized_text": "Photochemistry of Trace Atmospheric Gases with Components of Mineral Dust Aerosol”", "type": "title", "id": 1}, {"begin": 151, "end": 180, "text": "” Journal of Physical Chemi", "tokenized_text": "Journal of Physical Chemistry", "type": "venue", "id": 2}, {"begin": 183, "end": 187, "text": "y A ", "tokenized_text": "2011", "type": "year", "id": 3}]