[{"begin": 0, "end": 14, "text": "Cordray, D. S.", "tokenized_text": "Cordray , D . S .", "type": "authors", "id": 0}, {"begin": 16, "end": 20, "text": "1994", "tokenized_text": "1994", "type": "year", "id": 1}, {"begin": 23, "end": 110, "text": "Strengthening causal interpretation of non-experimental data: The role of meta-analysis", "tokenized_text": "Strengthening causal interpretation of non - experimental data : The role of meta - analysis", "type": "title", "id": 2}, {"begin": 112, "end": 148, "text": "New Directions in Program Evaluation", "tokenized_text": "New Directions in Program Evaluation", "type": "venue", "id": 3}]