[{"begin": 279, "end": 283, "text": "2013", "tokenized_text": "2013", "type": "year", "id": 0}, {"begin": 0, "end": 49, "text": "Chen S, Anderson T, Hewitt D, Tran A, Skafidas E.", "tokenized_text": "Chen S , Anderson T , Hewitt D , Tran A , Skafidas E .", "type": "authors", "id": 1}, {"begin": 50, "end": 143, "text": "Non-data-aided PMD monitoring for optical OFDM systems using low bandwidth coherent receivers", "tokenized_text": "Non - data - aided PMD monitoring for optical OFDM systems using low bandwidth coherent receivers", "type": "title", "id": 2}, {"begin": 145, "end": 149, "text": "2013", "tokenized_text": "2013", "type": "year", "id": 3}, {"begin": 150, "end": 253, "text": "Optical Fiber Communication Conference and Exposition and the National Fiber Optic Engineers Conference", "tokenized_text": "Optical Fiber Communication Conference and Exposition and the National Fiber Optic Engineers Conference", "type": "venue", "id": 4}]