{"comment": "//leave comments here if needed", "contain_publication_list": "F", "email": "Mark.Kohler@unisa.edu.au", "filename": "eed609bf-865e-42d9-90aa-4eeb20785b3f", "info": "T means true, F means False. If no publications, just leave the publication structure unchanged.", "is_personal_homepage": "T", "name": "Mark Kohler", "name_index": [{"index_in_file": [[64, 75]], "name_format": "Begin_First_Full End_Last_Full", "text": "Mark Kohler"}, {"in_email": "Before_At", "index_in_file": [[272, 283]], "name_format": "Begin_First_Full End_Last_Full", "text": "Mark.Kohler"}], "publications": [{"text": "COPY_SINGLE_PUBLICATION_HERE"}, {"text": "COPY_SINGLE_PUBLICATION_HERE"}], "url": "http://www.unisanet.unisa.edu.au/staff/Homepage.asp?Name=Mark.Kohler", "affiliation_info": [{"author_title": {"line_num": 9, "text": "Dr"}}, {"affiliation": {"line_num": 10, "text": "School of Psychology"}}, {"position": {"line_num": 10, "text": "Program Director"}}]}