[{"begin": 0, "end": 19, "text": "Lueder GT, Galli ML", "tokenized_text": "Lueder GT , Galli ML", "type": "authors", "id": 0}, {"begin": 22, "end": 124, "text": "Effect of preoperative stability of alignment on outcome of strabismus surgery for infantile esotropia", "tokenized_text": "Effect of preoperative stability of alignment on outcome of strabismus surgery for infantile esotropia", "type": "title", "id": 1}, {"begin": 127, "end": 134, "text": "J AAPOS", "tokenized_text": "J AAPOS", "type": "venue", "id": 2}, {"begin": 136, "end": 140, "text": "2008", "tokenized_text": "2008", "type": "year", "id": 3}]