[{"begin": 0, "end": 39, "text": "Wilson, N.H.M., J. Zhao, and A. Rahbee,", "tokenized_text": "Wilson , N . H . M . , J . Zhao , and A . Rahbee ,", "type": "authors", "id": 0}, {"begin": 40, "end": 133, "text": "“The Potential Impact of Automated Data Collection Systems on Urban Public Transport Planni", "tokenized_text": "“The Potential Impact of Automated Data Collection Systems on Urban Public Transport Planning", "type": "title", "id": 1}, {"begin": 134, "end": 157, "text": "g.” TRAIL Research Sc", "tokenized_text": "” TRAIL Research School", "type": "venue", "id": 2}, {"begin": 170, "end": 174, "text": "May ", "tokenized_text": "2005", "type": "year", "id": 3}]