[{"begin": 0, "end": 176, "text": "Seyer P, Vallois D, Poitry-Yamate C, Schütz F, Metref S, Tarussio D, Maechler P, Staels B, Lanz B, Gruetter R, Decaris J, Turner S, da Costa A, Preitner F, Minehira K, Foretz ", "tokenized_text": "Seyer P , Vallois D , Poitry - Yamate C , Schütz F , Metref S , Tarussio D , Maechler P , Staels B , Lanz B , Gruetter R , Decaris J , Turner S , da Costa A , Preitner F , Minehira K , Foretz M", "type": "authors", "id": 0}, {"begin": 176, "end": 192, "text": "M, and Thorens B", "tokenized_text": ", and Thorens B .", "type": "authors", "id": 1}, {"begin": 194, "end": 198, "text": "(201", "tokenized_text": "2013", "type": "year", "id": 2}, {"begin": 201, "end": 277, "text": " Hepatic glucose sensing is required to preserve beta-cell glucose competenc", "tokenized_text": "Hepatic glucose sensing is required to preserve beta - cell glucose competence", "type": "title", "id": 3}, {"begin": 279, "end": 292, "text": " J Clin Inves", "tokenized_text": "J Clin Invest", "type": "venue", "id": 4}]