[{"begin": 0, "end": 35, "text": "Scott, J. C., & Henderson, A. M. E.", "tokenized_text": "Scott , J . C . , & Henderson , A . M . E .", "type": "authors", "id": 0}, {"begin": 37, "end": 41, "text": "2013", "tokenized_text": "2013", "type": "year", "id": 1}, {"begin": 44, "end": 152, "text": "Language Matters: Thirteen-Month-Olds Understand That the Language a Speaker Uses Constrains Conventionality", "tokenized_text": "Language Matters : Thirteen - Month - Olds Understand That the Language a Speaker Uses Constrains Conventionality", "type": "title", "id": 2}, {"begin": 154, "end": 178, "text": "Developmental Psychology", "tokenized_text": "Developmental Psychology", "type": "venue", "id": 3}]