{"comment": "//leave comments here if needed", "contain_publication_list": "F", "email": "", "filename": "081a2952-c796-4d1d-aa8d-9e7c2cf72d31", "info": "T means true, F means False. If no publications, just leave the publication structure unchanged.", "is_personal_homepage": "T", "name": "Shoumo Bhattacharya", "name_index": [{"index_in_file": [[867, 878], [2470, 2481]], "name_format": "Begin_First_Full End_Last_Full", "text": "Matt Benson"}, {"index_in_file": [[140, 159], [4192, 4211]], "name_format": "Begin_First_Full End_Last_Full", "text": "Shoumo Bhattacharya"}, {"index_in_file": [[3082, 3096]], "name_format": "Begin_First_Full End_Last_Full", "text": "Linta Kucheria"}, {"index_in_file": [[2454, 2468]], "name_format": "Begin_First_Full End_Last_Full", "text": "Kamayani Singh"}, {"index_in_file": [[2738, 2750]], "name_format": "Begin_First_Full End_Last_Full", "text": "Paul Brennan"}, {"index_in_file": [[3038, 3052]], "name_format": "Begin_First_Full End_Last_Full", "text": "Dorota Szumska"}, {"index_in_file": [[3054, 3064]], "name_format": "Begin_First_Full End_Last_Full", "text": "Iain Dykes"}, {"index_in_file": [[2439, 2452]], "name_format": "Begin_First_Full End_Last_Full", "text": "Graham Davies"}, {"index_in_file": [[2483, 2494]], "name_format": "Begin_First_Full End_Last_Full", "text": "Adrian Gray"}, {"index_in_file": [[3066, 3080]], "name_format": "Begin_First_Full End_Last_Full", "text": "Rathi Puliyadi"}, {"index_in_file": [[4475, 4487]], "name_format": "Begin_Last_Full", "text": "Bhattacharya"}], "publications": [{"text": "COPY_SINGLE_PUBLICATION_HERE"}, {"text": "COPY_SINGLE_PUBLICATION_HERE"}], "url": "http://www.cardiov.ox.ac.uk/principal-investigators/researcher/shoumo-bhattacharya", "affiliation_info": [{"author_title": {"line_num": 11, "text": "Prof"}}, {"affiliation": {"line_num": 46, "text": "Medical Sciences Division"}}, {"position": {"line_num": 39, "text": "Chair"}}]}