[{"begin": 0, "end": 33, "text": "Tsoi, D., Porwal, M., Webster, A.", "tokenized_text": "Tsoi , D . , Porwal , M . , Webster , A .", "type": "authors", "id": 0}, {"begin": 35, "end": 39, "text": "2010", "tokenized_text": "2010", "type": "year", "id": 1}, {"begin": 42, "end": 166, "text": "Efficacy and safety of bupropion for smoking cessation and reduction in schizophrenia: a systematic review and meta-analysis", "tokenized_text": "Efficacy and safety of bupropion for smoking cessation and reduction in schizophrenia : a systematic review and meta - analysis", "type": "title", "id": 2}, {"begin": 168, "end": 197, "text": "British Journal of Psychiatry", "tokenized_text": "British Journal of Psychiatry", "type": "venue", "id": 3}]