[{"begin": 0, "end": 44, "text": "C Zhou, G FitzHarris, SL Alper, and JM Baltz", "tokenized_text": "C Zhou , G FitzHarris , SL Alper , and JM Baltz", "type": "authors", "id": 0}, {"begin": 46, "end": 50, "text": "2013", "tokenized_text": "2013", "type": "year", "id": 1}, {"begin": 53, "end": 180, "text": "Na+/H+ exchange is inactivated during mouse oocyte meiosis, facilitating glycine accumulation that maintains embryo cell volume", "tokenized_text": "Na + / H + exchange is inactivated during mouse oocyte meiosis , facilitating glycine accumulation that maintains embryo cell volume", "type": "title", "id": 2}, {"begin": 182, "end": 199, "text": "J. Cell. Physiol.", "tokenized_text": "J . Cell . Physiol .", "type": "venue", "id": 3}]