[{"begin": 0, "end": 82, "text": "Gubba SR, Ingham DB, Larsen KJ, Ma L, Pourkashanian M, Tan HZ, Williams A & Zhou H", "tokenized_text": "Gubba SR , Ingham DB , Larsen KJ , Ma L , Pourkashanian M , Tan HZ , Williams A & Zhou H", "type": "authors", "id": 0}, {"begin": 84, "end": 88, "text": "2012", "tokenized_text": "2012", "type": "year", "id": 1}, {"begin": 90, "end": 194, "text": "Numerical modelling of the co-firing of pulverised coal and straw in a 300 MWe tangentially fired boiler", "tokenized_text": "Numerical modelling of the co - firing of pulverised coal and straw in a 300 MWe tangentially fired boiler", "type": "title", "id": 2}, {"begin": 196, "end": 222, "text": "Fuel Processing Technology", "tokenized_text": "Fuel Processing Technology", "type": "venue", "id": 3}]