[{"begin": 0, "end": 47, "text": "Edge PJ, Heggs PJ, Pourkashanian M & Williams A", "tokenized_text": "Edge PJ , Heggs PJ , Pourkashanian M & Williams A", "type": "authors", "id": 0}, {"begin": 49, "end": 53, "text": "2011", "tokenized_text": "2011", "type": "year", "id": 1}, {"begin": 55, "end": 136, "text": "A CFD-process model of steam generation in a power plant by a thermosyphon system", "tokenized_text": "A CFD - process model of steam generation in a power plant by a thermosyphon system", "type": "title", "id": 2}, {"begin": 138, "end": 173, "text": "Computer Aided Chemical Engineering", "tokenized_text": "Computer Aided Chemical Engineering", "type": "venue", "id": 3}]