{"comment": "//leave comments here if needed", "contain_publication_list": "F", "email": "sabrina.sartori@its.uio.no", "filename": "c8a5d042-3384-45e9-91a2-c4089e46b7c6", "info": "T means true, F means False. If no publications, just leave the publication structure unchanged.", "is_personal_homepage": "T", "name": "Sabrina Sartori", "name_index": [{"index_in_file": [[414, 429], [442, 457]], "name_format": "Begin_First_Full End_Last_Full", "text": "Sabrina Sartori"}, {"in_email": "BEFORE_AT", "index_in_file": [[544, 559]], "name_format": "Begin_First_Full End_Last_Full", "text": "sabrina.sartori"}, {"in_email": "BEFORE_AT", "index_in_file": [[3868, 3882]], "name_format": "Begin_First_Full_Last_Full", "text": "sabrinasartori"}, {"index_in_file": [[4791, 4805]], "name_format": "Begin_First_Full End_Last_Full", "text": "Kristin Scheen"}], "publications": [{"text": "COPY_SINGLE_PUBLICATION_HERE"}, {"text": "COPY_SINGLE_PUBLICATION_HERE"}], "url": "http://www.mn.uio.no/fysikk/english/people/aca/sabrinsa/index.html", "affiliation_info": [{"author_title": {"line_num": 54, "text": "Post doc"}}, {"affiliation": {"line_num": 5, "text": "Department of Technology Systems"}}, {"position": {"line_num": 22, "text": "Associate Professor"}}]}