[{"begin": 0, "end": 54, "text": "B. G. Breitmeyer, M. H. Herzog, H. Ogmen, ‚ÄúMotion, n", "tokenized_text": "B . G . Breitmeyer , M . H . Herzog , H . Ogmen , ‚ÄúMotion , not", "type": "authors", "id": 0}, {"begin": 55, "end": 62, "text": "t Maski", "tokenized_text": "Masking", "type": "title", "id": 1}, {"begin": 64, "end": 108, "text": ", Provides the Medium for Feature Attributio", "tokenized_text": "Provides the Medium for Feature Attribution‚Äù", "type": "title", "id": 2}, {"begin": 110, "end": 131, "text": "Äù, PSYCHOLOGICAL SCI", "tokenized_text": "PSYCHOLOGICAL SCIENCE", "type": "venue", "id": 3}, {"begin": 156, "end": 160, "text": "29, ", "tokenized_text": "2008", "type": "year", "id": 4}]